README.rst
setup.py
src/calendar_cli/__init__.py
src/calendar_cli/calendar_cli.py
src/calendar_cli/i18n/__init__.py
src/calendar_cli/i18n/messages_en.py
src/calendar_cli/i18n/messages_ja.py
src/calendar_cli/model/__init__.py
src/calendar_cli/model/event.py
src/calendar_cli/operation/__init__.py
src/calendar_cli/operation/create_operation.py
src/calendar_cli/operation/help_operation.py
src/calendar_cli/operation/operation.py
src/calendar_cli/operation/setup_operation.py
src/calendar_cli/operation/summary_operation.py
src/calendar_cli/service/__init__.py
src/calendar_cli/service/google_calendar_service.py
src/calendar_cli/setting/__init__.py
src/calendar_cli/setting/arg_parser.py
src/calendar_cli/setting/setting.py
src/gcalendar_cli.egg-info/PKG-INFO
src/gcalendar_cli.egg-info/SOURCES.txt
src/gcalendar_cli.egg-info/dependency_links.txt
src/gcalendar_cli.egg-info/entry_points.txt
src/gcalendar_cli.egg-info/requires.txt
src/gcalendar_cli.egg-info/top_level.txt