Metadata-Version: 1.0
Name: gcalendar-cli
Version: 0.2.3
Summary: Command-line Interface for Google Calendar
Home-page: https://github.com/mogproject/calendar-cli
Author: mogproject
Author-email: mogproj@gmail.com
License: Apache 2.0 License
Platform: UNKNOWN
